{
  "annotations": {
    "list": []
  },
  "editable": true,
  "fiscalYearStartMonth": 0,
  "graphTooltip": 0,
  "id": null,
  "links": [],
  "liveNow": false,
  "panels": [
    {
      "datasource": {
        "type": "postgres",
        "uid": "emsn_postgres"
      },
      "fieldConfig": {
        "defaults": {
          "color": {
            "mode": "palette-classic"
          },
          "mappings": [],
          "thresholds": {
            "mode": "absolute",
            "steps": [
              { "color": "green", "value": null }
            ]
          },
          "unit": "short"
        },
        "overrides": []
      },
      "gridPos": { "h": 4, "w": 6, "x": 0, "y": 0 },
      "id": 1,
      "options": {
        "colorMode": "value",
        "graphMode": "area",
        "justifyMode": "auto",
        "orientation": "auto",
        "reduceOptions": {
          "calcs": ["lastNotNull"],
          "fields": "",
          "values": false
        },
        "textMode": "auto"
      },
      "pluginVersion": "10.0.0",
      "targets": [
        {
          "datasource": { "type": "postgres", "uid": "emsn_postgres" },
          "format": "table",
          "rawSql": "SELECT COUNT(*) as total FROM media_archive",
          "refId": "A"
        }
      ],
      "title": "Totaal Opnames",
      "type": "stat"
    },
    {
      "datasource": {
        "type": "postgres",
        "uid": "emsn_postgres"
      },
      "fieldConfig": {
        "defaults": {
          "color": {
            "mode": "palette-classic"
          },
          "mappings": [],
          "thresholds": {
            "mode": "absolute",
            "steps": [
              { "color": "green", "value": null }
            ]
          },
          "unit": "short"
        },
        "overrides": []
      },
      "gridPos": { "h": 4, "w": 6, "x": 6, "y": 0 },
      "id": 2,
      "options": {
        "colorMode": "value",
        "graphMode": "none",
        "justifyMode": "auto",
        "orientation": "auto",
        "reduceOptions": {
          "calcs": ["lastNotNull"],
          "fields": "",
          "values": false
        },
        "textMode": "auto"
      },
      "pluginVersion": "10.0.0",
      "targets": [
        {
          "datasource": { "type": "postgres", "uid": "emsn_postgres" },
          "format": "table",
          "rawSql": "SELECT COUNT(DISTINCT species) as soorten FROM media_archive",
          "refId": "A"
        }
      ],
      "title": "Unieke Soorten",
      "type": "stat"
    },
    {
      "datasource": {
        "type": "postgres",
        "uid": "emsn_postgres"
      },
      "fieldConfig": {
        "defaults": {
          "color": {
            "mode": "palette-classic"
          },
          "mappings": [],
          "thresholds": {
            "mode": "absolute",
            "steps": [
              { "color": "green", "value": null }
            ]
          },
          "unit": "decgbytes"
        },
        "overrides": []
      },
      "gridPos": { "h": 4, "w": 6, "x": 12, "y": 0 },
      "id": 3,
      "options": {
        "colorMode": "value",
        "graphMode": "none",
        "justifyMode": "auto",
        "orientation": "auto",
        "reduceOptions": {
          "calcs": ["lastNotNull"],
          "fields": "",
          "values": false
        },
        "textMode": "auto"
      },
      "pluginVersion": "10.0.0",
      "targets": [
        {
          "datasource": { "type": "postgres", "uid": "emsn_postgres" },
          "format": "table",
          "rawSql": "SELECT ROUND(SUM(file_size_bytes)::numeric / 1073741824, 2) as gb FROM media_archive",
          "refId": "A"
        }
      ],
      "title": "Archief Grootte",
      "type": "stat"
    },
    {
      "datasource": {
        "type": "postgres",
        "uid": "emsn_postgres"
      },
      "fieldConfig": {
        "defaults": {
          "mappings": [],
          "thresholds": {
            "mode": "absolute",
            "steps": [
              { "color": "green", "value": null }
            ]
          },
          "color": {
            "mode": "palette-classic"
          }
        },
        "overrides": []
      },
      "gridPos": { "h": 4, "w": 6, "x": 18, "y": 0 },
      "id": 4,
      "options": {
        "legend": { "displayMode": "list", "placement": "bottom", "showLegend": false },
        "pieType": "pie",
        "reduceOptions": {
          "calcs": ["lastNotNull"],
          "fields": "",
          "values": true
        },
        "tooltip": { "mode": "single" }
      },
      "pluginVersion": "10.0.0",
      "targets": [
        {
          "datasource": { "type": "postgres", "uid": "emsn_postgres" },
          "format": "table",
          "rawSql": "SELECT station as \"Station\", COUNT(*) as \"Aantal\" FROM media_archive GROUP BY station ORDER BY station",
          "refId": "A"
        }
      ],
      "title": "Per Station",
      "type": "piechart"
    },
    {
      "datasource": {
        "type": "postgres",
        "uid": "emsn_postgres"
      },
      "fieldConfig": {
        "defaults": {
          "color": {
            "mode": "palette-classic"
          },
          "custom": {
            "hideFrom": {
              "legend": false,
              "tooltip": false,
              "viz": false
            }
          },
          "mappings": []
        },
        "overrides": []
      },
      "gridPos": { "h": 8, "w": 12, "x": 0, "y": 4 },
      "id": 5,
      "options": {
        "legend": {
          "displayMode": "table",
          "placement": "right",
          "showLegend": true,
          "values": ["value", "percent"]
        },
        "pieType": "donut",
        "reduceOptions": {
          "calcs": ["lastNotNull"],
          "fields": "",
          "values": true
        },
        "tooltip": {
          "mode": "single",
          "sort": "none"
        }
      },
      "pluginVersion": "10.0.0",
      "targets": [
        {
          "datasource": { "type": "postgres", "uid": "emsn_postgres" },
          "format": "table",
          "rawSql": "SELECT species, COUNT(*) as count FROM media_archive GROUP BY species ORDER BY count DESC LIMIT 15",
          "refId": "A"
        }
      ],
      "title": "Top 15 Soorten",
      "type": "piechart"
    },
    {
      "datasource": {
        "type": "postgres",
        "uid": "emsn_postgres"
      },
      "fieldConfig": {
        "defaults": {
          "color": {
            "mode": "palette-classic"
          },
          "custom": {
            "axisCenteredZero": false,
            "axisColorMode": "text",
            "axisLabel": "",
            "axisPlacement": "auto",
            "barAlignment": 0,
            "drawStyle": "bars",
            "fillOpacity": 80,
            "gradientMode": "none",
            "hideFrom": {
              "legend": false,
              "tooltip": false,
              "viz": false
            },
            "lineInterpolation": "linear",
            "lineWidth": 1,
            "pointSize": 5,
            "scaleDistribution": {
              "type": "linear"
            },
            "showPoints": "never",
            "spanNulls": false,
            "stacking": {
              "group": "A",
              "mode": "none"
            },
            "thresholdsStyle": {
              "mode": "off"
            }
          },
          "mappings": [],
          "thresholds": {
            "mode": "absolute",
            "steps": [
              { "color": "green", "value": null }
            ]
          }
        },
        "overrides": []
      },
      "gridPos": { "h": 8, "w": 12, "x": 12, "y": 4 },
      "id": 6,
      "options": {
        "legend": {
          "calcs": [],
          "displayMode": "list",
          "placement": "bottom",
          "showLegend": true
        },
        "tooltip": {
          "mode": "single",
          "sort": "none"
        }
      },
      "pluginVersion": "10.0.0",
      "targets": [
        {
          "datasource": { "type": "postgres", "uid": "emsn_postgres" },
          "format": "time_series",
          "rawSql": "SELECT DATE_TRUNC('day', detection_date) as time, COUNT(*) as opnames FROM media_archive WHERE detection_date >= NOW() - INTERVAL '30 days' GROUP BY DATE_TRUNC('day', detection_date) ORDER BY time",
          "refId": "A"
        }
      ],
      "title": "Opnames per Dag (30 dagen)",
      "type": "timeseries"
    },
    {
      "datasource": {
        "type": "postgres",
        "uid": "emsn_postgres"
      },
      "description": "Selecteer een soort om opnames te bekijken",
      "fieldConfig": {
        "defaults": {
          "color": {
            "mode": "thresholds"
          },
          "custom": {
            "align": "auto",
            "cellOptions": {
              "type": "auto"
            },
            "inspect": false
          },
          "mappings": [],
          "thresholds": {
            "mode": "absolute",
            "steps": [
              { "color": "green", "value": null }
            ]
          }
        },
        "overrides": [
          {
            "matcher": { "id": "byName", "options": "Audio" },
            "properties": [
              {
                "id": "custom.cellOptions",
                "value": {
                  "type": "link"
                }
              },
              {
                "id": "links",
                "value": [
                  {
                    "title": "Afspelen",
                    "url": "http://192.168.1.178:8081/api/archive/audio/${__data.fields.id}",
                    "targetBlank": true
                  }
                ]
              }
            ]
          },
          {
            "matcher": { "id": "byName", "options": "Spectrogram" },
            "properties": [
              {
                "id": "links",
                "value": [
                  {
                    "title": "Bekijken",
                    "url": "http://192.168.1.178:8081/api/archive/spectrogram/${__data.fields.id}",
                    "targetBlank": true
                  }
                ]
              }
            ]
          }
        ]
      },
      "gridPos": { "h": 12, "w": 24, "x": 0, "y": 12 },
      "id": 7,
      "options": {
        "cellHeight": "sm",
        "enablePagination": true,
        "footer": {
          "countRows": true,
          "fields": "",
          "reducer": ["sum"],
          "show": true
        },
        "frameIndex": 0,
        "showHeader": true,
        "showTypeIcons": false,
        "sortBy": [
          {
            "desc": true,
            "displayName": "Datum"
          }
        ]
      },
      "pluginVersion": "10.0.0",
      "targets": [
        {
          "datasource": { "type": "postgres", "uid": "emsn_postgres" },
          "format": "table",
          "rawSql": "SELECT ma.id, ma.species as \"Soort\", ma.station as \"Station\", TO_CHAR(ma.detection_date, 'YYYY-MM-DD') as \"Datum\", ROUND(ma.confidence::numeric * 100)::text || '%' as \"Confidence\", '▶ Play' as \"Audio\", '📊 View' as \"Spectrogram\" FROM media_archive ma ORDER BY ma.species, ma.detection_date DESC LIMIT 1000",
          "refId": "A"
        }
      ],
      "title": "Opnames Browser",
      "transformations": [],
      "type": "table"
    }
  ],
  "refresh": "5m",
  "schemaVersion": 38,
  "style": "dark",
  "tags": ["emsn", "audio", "archive", "birdnet"],
  "templating": {
    "list": []
  },
  "time": {
    "from": "now-30d",
    "to": "now"
  },
  "timepicker": {},
  "timezone": "browser",
  "title": "EMSN Audio Archief",
  "uid": "emsn-audio-archive-v2",
  "version": 1,
  "weekStart": "monday"
}
